SoutyUI/__init__.py
SoutyUI/components.py
SoutyUI/core.py
SoutyUI/styles.py
soutyui-0.1.0.dist-info/licenses/LICENSE
soutyui-0.1.0.dist-info/METADATA
soutyui-0.1.0.dist-info/WHEEL
soutyui-0.1.0.dist-info/top_level.txt
soutyui-0.1.0.dist-info/RECORD
