Metadata-Version: 2.4
Name: SoutyUI
Version: 0.1.0
Summary: A futuristic Python UI framework better than PyQt and NiceGUI 🚀
Home-page: https://github.com/q9tx/SoutyUI
Author: q9tx
Author-email: xctq9tx@gmail.com
Classifier: Programming Language :: Python :: 3
Classifier: License :: OSI Approved :: MIT License
Classifier: Operating System :: OS Independent
Requires-Python: >=3.7
License-File: LICENSE
Dynamic: author
Dynamic: author-email
Dynamic: classifier
Dynamic: home-page
Dynamic: license-file
Dynamic: requires-python
Dynamic: summary
